mmc_jwt_auth/__init__.py
mmc_jwt_auth/auth.py
mmc_jwt_auth-2.0.2.dist-info/METADATA
mmc_jwt_auth-2.0.2.dist-info/WHEEL
mmc_jwt_auth-2.0.2.dist-info/top_level.txt
mmc_jwt_auth-2.0.2.dist-info/RECORD
